Workbook

Sheet Couverture
B2: On mange quoi / Fidelity — Modèle financier 12 mois, 3 scénarios
B3: Pessimiste · Réaliste · Ambitieux — 31 août 2026
B5: Vue d'ensemble — année 1
B6: Scénario | C6: CA année | D6: Résultat net | E6: Trésorerie fin M12
B7: Pessimiste (gratter le fond) | C7: ='Modèle'!Q28 | D7: ='Modèle'!Q36 | E7: ='Modèle'!P37
B8: Réaliste | C8: ='Réaliste'!Q28 | D8: ='Réaliste'!Q36 | E8: ='Réaliste'!P37
B9: Ambitieux | C9: ='Ambitieux'!Q28 | D9: ='Ambitieux'!Q36 | E9: ='Ambitieux'!P37
B11: Détails fin M12
B12: Scénario | C12: Restos actifs | D12: Restos premium | E12: Mois bénéficiaires
B13: Pessimiste (gratter le fond) | C13: ='Modèle'!P20 | D13: ='Modèle'!P22 | E13: =COUNTIF('Modèle'!E36:P36,">0")&" / 12"
B14: Réaliste | C14: ='Réaliste'!P20 | D14: ='Réaliste'!P22 | E14: =COUNTIF('Réaliste'!E36:P36,">0")&" / 12"
B15: Ambitieux | C15: ='Ambitieux'!P20 | D15: ='Ambitieux'!P22 | E15: =COUNTIF('Ambitieux'!E36:P36,">0")&" / 12"
B17: Contenu du classeur
B18: Modèle | C18: Scénario pessimiste : croissance minimale, 9 restos fin M12, aucun white-label
B19: Réaliste | C19: Bouche-à-oreille correct dans une ville : 38 restos fin M12, 1 contrat white-label
B20: Ambitieux | C20: Ça prend : 125 restos fin M12, white-label + pub dès le 2e semestre
B22: Mode d'emploi
B23: Chaque scénario est autonome : ses hypothèses (cellules bleues) sont en haut de sa feuille.
B24: Modifiez une cellule bleue, toute la feuille se recalcule.
B25: Convention couleurs : bleu = saisie, noir = calcul, vert = référence à une autre feuille.

Sheet Modèle
B2: Scénario pessimiste — hypothèses et projection 12 mois
B4: Paramètre | C4: Valeur | D4: Note
B5: Prix abonnement premium (€/mois) | C5: 19 | D5: Fourchette basse
B6: Frais par récompense débloquée (€) | C6: 0.3 | D6: Prélevé uniquement quand un client utilise sa récompense
B7: Récompenses débloquées / restaurant actif / mois | C7: 6 | D7: Base clients très petite
B8: Commission Stripe variable (%) | C8: 0.015 | D8: Sur les abonnements encaissés
B9: Commission Stripe fixe (€/abonné/mois) | C9: 0.25 | D9: Par restaurant premium facturé
B10: Nom de domaine (€/mois) | C10: 0.83 | D10: ~10 €/an lissés
B11: Apple Developer (€/mois) | C11: 7.75 | D11: 99 $/an ≈ 93 €/an, lissés
B12: Mois d'activation Apple Developer | C12: 4 | D12: Phase 2 Wallet
B13: Infra au-delà des free tiers (€/mois) | C13: 22 | D13: Free tiers longtemps suffisants
B14: Mois de bascule infra payante | C14: 9 | D14: Croissance lente = bascule tardive
B16: Projection mensuelle
D17: N° du mois | E17: 1 | F17: 2 | G17: 3 | H17: 4 | I17: 5 | J17: 6 | K17: 7 | L17: 8 | M17: 9 | N17: 10 | O17: 11 | P17: 12
D18: Ligne | E18: M1 | F18: M2 | G18: M3 | H18: M4 | I18: M5 | J18: M6 | K18: M7 | L18: M8 | M18: M9 | N18: M10 | O18: M11 | P18: M12 | Q18: Total
D19: VOLUME
D20: Restaurants actifs (saisie) | E20: 1 | F20: 1 | G20: 2 | H20: 2 | I20: 3 | J20: 4 | K20: 4 | L20: 5 | M20: 6 | N20: 7 | O20: 8 | P20: 9 | Q20: =P20
D21: Taux de conversion premium (saisie) | E21: 0 | F21: 0 | G21: 0 | H21: 0.05 | I21: 0.05 | J21: 0.08 | K21: 0.08 | L21: 0.1 | M21: 0.1 | N21: 0.12 | O21: 0.12 | P21: 0.15
D22: Restaurants premium | E22: =E20*E21 | F22: =F20*F21 | G22: =G20*G21 | H22: =H20*H21 | I22: =I20*I21 | J22: =J20*J21 | K22: =K20*K21 | L22: =L20*L21 | ... P22: =P20*P21
D23: Récompenses débloquées dans le mois | E23: =E20*$C$7 | F23: =F20*$C$7 | G23: =G20*$C$7 | H23: =H20*$C$7 | I23: =I20*$C$7 | J23: =J20*$C$7 | K23: =K20*$C$7 | L23: =L20*$C$7 | ... P23: =P20*$C$7 | Q23: =SUM(E23:P23)
D24: REVENUS (€)
D25: Abonnements premium | E25: =E22*$C$5 | F25: =F22*$C$5 | G25: =G22*$C$5 | H25: =H22*$C$5 | I25: =I22*$C$5 | J25: =J22*$C$5 | K25: =K22*$C$5 | L25: =L22*$C$5 | ... P25: =P22*$C$5 | Q25: =SUM(E25:P25)
D26: Frais sur récompenses débloquées | E26: =E23*$C$6 | F26: =F23*$C$6 | G26: =G23*$C$6 | H26: =H23*$C$6 | I26: =I23*$C$6 | J26: =J23*$C$6 | K26: =K23*$C$6 | L26: =L23*$C$6 | ... P26: =P23*$C$6 | Q26: =SUM(E26:P26)
D27: White-label / pub (saisie) | E27: 0 | F27: 0 | G27: 0 | H27: 0 | I27: 0 | J27: 0 | K27: 0 | L27: 0 | M27: 0 | N27: 0 | O27: 0 | P27: 0 | Q27: =SUM(E27:P27)
D28: CA total | E28: =SUM(E25:E27) | F28: =SUM(F25:F27) | G28: =SUM(G25:G27) | H28: =SUM(H25:H27) | I28: =SUM(I25:I27) | J28: =SUM(J25:J27) | K28: =SUM(K25:K27) | L28: =SUM(L25:L27) | ... P28: =SUM(P25:P27) | Q28: =SUM(E28:P28)
D29: COÛTS (€)
D30: Infra (hébergement, BDD, stockage) | E30: =IF(E$17>=$C$14,$C$13,0) | F30: =IF(F$17>=$C$14,$C$13,0) | G30: =IF(G$17>=$C$14,$C$13,0) | H30: =IF(H$17>=$C$14,$C$13,0) | I30: =IF(I$17>=$C$14,$C$13,0) | J30: =IF(J$17>=$C$14,$C$13,0) | K30: =IF(K$17>=$C$14,$C$13,0) | L30: =IF(L$17>=$C$14,$C$13,0) | ... P30: =IF(P$17>=$C$14,$C$13,0) | Q30: =SUM(E30:P30)
D31: Apple Developer | E31: =IF(E$17>=$C$12,$C$11,0) | F31: =IF(F$17>=$C$12,$C$11,0) | G31: =IF(G$17>=$C$12,$C$11,0) | H31: =IF(H$17>=$C$12,$C$11,0) | I31: =IF(I$17>=$C$12,$C$11,0) | J31: =IF(J$17>=$C$12,$C$11,0) | K31: =IF(K$17>=$C$12,$C$11,0) | L31: =IF(L$17>=$C$12,$C$11,0) | ... P31: =IF(P$17>=$C$12,$C$11,0) | Q31: =SUM(E31:P31)
D32: Nom de domaine | E32: =$C$10 | F32: =$C$10 | G32: =$C$10 | H32: =$C$10 | I32: =$C$10 | J32: =$C$10 | K32: =$C$10 | L32: =$C$10 | ... P32: =$C$10 | Q32: =SUM(E32:P32)
D33: Commissions Stripe | E33: =E25*$C$8+E22*$C$9 | F33: =F25*$C$8+F22*$C$9 | G33: =G25*$C$8+G22*$C$9 | H33: =H25*$C$8+H22*$C$9 | I33: =I25*$C$8+I22*$C$9 | J33: =J25*$C$8+J22*$C$9 | K33: =K25*$C$8+K22*$C$9 | L33: =L25*$C$8+L22*$C$9 | ... P33: =P25*$C$8+P22*$C$9 | Q33: =SUM(E33:P33)
D34: Coûts totaux | E34: =SUM(E30:E33) | F34: =SUM(F30:F33) | G34: =SUM(G30:G33) | H34: =SUM(H30:H33) | I34: =SUM(I30:I33) | J34: =SUM(J30:J33) | K34: =SUM(K30:K33) | L34: =SUM(L30:L33) | ... P34: =SUM(P30:P33) | Q34: =SUM(E34:P34)
D35: RÉSULTAT
D36: Résultat net du mois | E36: =E28-E34 | F36: =F28-F34 | G36: =G28-G34 | H36: =H28-H34 | I36: =I28-I34 | J36: =J28-J34 | K36: =K28-K34 | L36: =L28-L34 | ... P36: =P28-P34 | Q36: =SUM(E36:P36)
D37: Trésorerie cumulée | E37: =E36 | F37: =E37+F36 | G37: =F37+G36 | H37: =G37+H36 | I37: =H37+I36 | J37: =I37+J36 | K37: =J37+K36 | L37: =K37+L36 | M37: =L37+M36 | ... P37: =O37+P36

Sheet Réaliste
B2: Scénario réaliste — hypothèses et projection 12 mois
B4: Paramètre | C4: Valeur | D4: Note
B5: Prix abonnement premium (€/mois) | C5: 24 | D5: Milieu de fourchette 19-29 €
B6: Frais par récompense débloquée (€) | C6: 0.3 | D6: Prélevé uniquement quand un client utilise sa récompense
B7: Récompenses débloquées / restaurant actif / mois | C7: 12 | D7: Base clients en croissance
B8: Commission Stripe variable (%) | C8: 0.015 | D8: Sur les abonnements encaissés
B9: Commission Stripe fixe (€/abonné/mois) | C9: 0.25 | D9: Par restaurant premium facturé
B10: Nom de domaine (€/mois) | C10: 0.83 | D10: ~10 €/an lissés
B11: Apple Developer (€/mois) | C11: 7.75 | D11: 99 $/an ≈ 93 €/an, lissés
B12: Mois d'activation Apple Developer | C12: 3 | D12: Wallet activé tôt
B13: Infra au-delà des free tiers (€/mois) | C13: 30 | D13: Dépassement free tiers vers ~500 utilisateurs actifs
B14: Mois de bascule infra payante | C14: 6 | D14: La courbe d'usage le justifie
B16: Projection mensuelle
D17: N° du mois | E17: 1 | F17: 2 | G17: 3 | H17: 4 | I17: 5 | J17: 6 | K17: 7 | L17: 8 | M17: 9 | N17: 10 | O17: 11 | P17: 12
D18: Ligne | E18: M1 | F18: M2 | G18: M3 | H18: M4 | I18: M5 | J18: M6 | K18: M7 | L18: M8 | M18: M9 | N18: M10 | O18: M11 | P18: M12 | Q18: Total
D19: VOLUME
D20: Restaurants actifs (saisie) | E20: 1 | F20: 2 | G20: 3 | H20: 5 | I20: 7 | J20: 10 | K20: 13 | L20: 16 | M20: 20 | N20: 25 | O20: 30 | P20: 38 | Q20: =P20
D21: Taux de conversion premium (saisie) | E21: 0 | F21: 0 | G21: 0.05 | H21: 0.08 | I21: 0.1 | J21: 0.12 | K21: 0.15 | L21: 0.18 | M21: 0.2 | N21: 0.22 | O21: 0.25 | P21: 0.28
D22: Restaurants premium | E22: =E20*E21 | F22: =F20*F21 | G22: =G20*G21 | H22: =H20*H21 | I22: =I20*I21 | J22: =J20*J21 | K22: =K20*K21 | L22: =L20*L21 | ... P22: =P20*P21
D23: Récompenses débloquées dans le mois | E23: =E20*$C$7 | F23: =F20*$C$7 | G23: =G20*$C$7 | H23: =H20*$C$7 | I23: =I20*$C$7 | J23: =J20*$C$7 | K23: =K20*$C$7 | L23: =L20*$C$7 | ... P23: =P20*$C$7 | Q23: =SUM(E23:P23)
D24: REVENUS (€)
D25: Abonnements premium | E25: =E22*$C$5 | F25: =F22*$C$5 | G25: =G22*$C$5 | H25: =H22*$C$5 | I25: =I22*$C$5 | J25: =J22*$C$5 | K25: =K22*$C$5 | L25: =L22*$C$5 | ... P25: =P22*$C$5 | Q25: =SUM(E25:P25)
D26: Frais sur récompenses débloquées | E26: =E23*$C$6 | F26: =F23*$C$6 | G26: =G23*$C$6 | H26: =H23*$C$6 | I26: =I23*$C$6 | J26: =J23*$C$6 | K26: =K23*$C$6 | L26: =L23*$C$6 | ... P26: =P23*$C$6 | Q26: =SUM(E26:P26)
D27: White-label / pub (saisie) | E27: 0 | F27: 0 | G27: 0 | H27: 0 | I27: 0 | J27: 0 | K27: 0 | L27: 0 | M27: 0 | N27: 500 | O27: 500 | P27: 500 | Q27: =SUM(E27:P27)
D28: CA total | E28: =SUM(E25:E27) | F28: =SUM(F25:F27) | G28: =SUM(G25:G27) | H28: =SUM(H25:H27) | I28: =SUM(I25:I27) | J28: =SUM(J25:J27) | K28: =SUM(K25:K27) | L28: =SUM(L25:L27) | ... P28: =SUM(P25:P27) | Q28: =SUM(E28:P28)
D29: COÛTS (€)
D30: Infra (hébergement, BDD, stockage) | E30: =IF(E$17>=$C$14,$C$13,0) | F30: =IF(F$17>=$C$14,$C$13,0) | G30: =IF(G$17>=$C$14,$C$13,0) | H30: =IF(H$17>=$C$14,$C$13,0) | I30: =IF(I$17>=$C$14,$C$13,0) | J30: =IF(J$17>=$C$14,$C$13,0) | K30: =IF(K$17>=$C$14,$C$13,0) | L30: =IF(L$17>=$C$14,$C$13,0) | ... P30: =IF(P$17>=$C$14,$C$13,0) | Q30: =SUM(E30:P30)
D31: Apple Developer | E31: =IF(E$17>=$C$12,$C$11,0) | F31: =IF(F$17>=$C$12,$C$11,0) | G31: =IF(G$17>=$C$12,$C$11,0) | H31: =IF(H$17>=$C$12,$C$11,0) | I31: =IF(I$17>=$C$12,$C$11,0) | J31: =IF(J$17>=$C$12,$C$11,0) | K31: =IF(K$17>=$C$12,$C$11,0) | L31: =IF(L$17>=$C$12,$C$11,0) | ... P31: =IF(P$17>=$C$12,$C$11,0) | Q31: =SUM(E31:P31)
D32: Nom de domaine | E32: =$C$10 | F32: =$C$10 | G32: =$C$10 | H32: =$C$10 | I32: =$C$10 | J32: =$C$10 | K32: =$C$10 | L32: =$C$10 | ... P32: =$C$10 | Q32: =SUM(E32:P32)
D33: Commissions Stripe | E33: =E25*$C$8+E22*$C$9 | F33: =F25*$C$8+F22*$C$9 | G33: =G25*$C$8+G22*$C$9 | H33: =H25*$C$8+H22*$C$9 | I33: =I25*$C$8+I22*$C$9 | J33: =J25*$C$8+J22*$C$9 | K33: =K25*$C$8+K22*$C$9 | L33: =L25*$C$8+L22*$C$9 | ... P33: =P25*$C$8+P22*$C$9 | Q33: =SUM(E33:P33)
D34: Coûts totaux | E34: =SUM(E30:E33) | F34: =SUM(F30:F33) | G34: =SUM(G30:G33) | H34: =SUM(H30:H33) | I34: =SUM(I30:I33) | J34: =SUM(J30:J33) | K34: =SUM(K30:K33) | L34: =SUM(L30:L33) | ... P34: =SUM(P30:P33) | Q34: =SUM(E34:P34)
D35: RÉSULTAT
D36: Résultat net du mois | E36: =E28-E34 | F36: =F28-F34 | G36: =G28-G34 | H36: =H28-H34 | I36: =I28-I34 | J36: =J28-J34 | K36: =K28-K34 | L36: =L28-L34 | ... P36: =P28-P34 | Q36: =SUM(E36:P36)
D37: Trésorerie cumulée | E37: =E36 | F37: =E37+F36 | G37: =F37+G36 | H37: =G37+H36 | I37: =H37+I36 | J37: =I37+J36 | K37: =J37+K36 | L37: =K37+L36 | M37: =L37+M36 | ... P37: =O37+P36

Sheet Ambitieux
B2: Scénario ambitieux — hypothèses et projection 12 mois
B4: Paramètre | C4: Valeur | D4: Note
B5: Prix abonnement premium (€/mois) | C5: 29 | D5: Haut de fourchette, services inclus (photoshoot…)
B6: Frais par récompense débloquée (€) | C6: 0.3 | D6: Prélevé uniquement quand un client utilise sa récompense
B7: Récompenses débloquées / restaurant actif / mois | C7: 20 | D7: Usage intensif, FOODSHARE actif
B8: Commission Stripe variable (%) | C8: 0.015 | D8: Sur les abonnements encaissés
B9: Commission Stripe fixe (€/abonné/mois) | C9: 0.25 | D9: Par restaurant premium facturé
B10: Nom de domaine (€/mois) | C10: 0.83 | D10: ~10 €/an lissés
B11: Apple Developer (€/mois) | C11: 7.75 | D11: 99 $/an ≈ 93 €/an, lissés
B12: Mois d'activation Apple Developer | C12: 2 | D12: Wallet dès le début
B13: Infra au-delà des free tiers (€/mois) | C13: 45 | D13: Pic d'usage + stockage images
B14: Mois de bascule infra payante | C14: 4 | D14: Trafic précoce
B16: Projection mensuelle
D17: N° du mois | E17: 1 | F17: 2 | G17: 3 | H17: 4 | I17: 5 | J17: 6 | K17: 7 | L17: 8 | M17: 9 | N17: 10 | O17: 11 | P17: 12
D18: Ligne | E18: M1 | F18: M2 | G18: M3 | H18: M4 | I18: M5 | J18: M6 | K18: M7 | L18: M8 | M18: M9 | N18: M10 | O18: M11 | P18: M12 | Q18: Total
D19: VOLUME
D20: Restaurants actifs (saisie) | E20: 2 | F20: 4 | G20: 7 | H20: 12 | I20: 18 | J20: 26 | K20: 36 | L20: 48 | M20: 62 | N20: 80 | O20: 100 | P20: 125 | Q20: =P20
D21: Taux de conversion premium (saisie) | E21: 0 | F21: 0.05 | G21: 0.08 | H21: 0.12 | I21: 0.15 | J21: 0.18 | K21: 0.22 | L21: 0.25 | M21: 0.28 | N21: 0.32 | O21: 0.35 | P21: 0.38
D22: Restaurants premium | E22: =E20*E21 | F22: =F20*F21 | G22: =G20*G21 | H22: =H20*H21 | I22: =I20*I21 | J22: =J20*J21 | K22: =K20*K21 | L22: =L20*L21 | ... P22: =P20*P21
D23: Récompenses débloquées dans le mois | E23: =E20*$C$7 | F23: =F20*$C$7 | G23: =G20*$C$7 | H23: =H20*$C$7 | I23: =I20*$C$7 | J23: =J20*$C$7 | K23: =K20*$C$7 | L23: =L20*$C$7 | ... P23: =P20*$C$7 | Q23: =SUM(E23:P23)
D24: REVENUS (€)
D25: Abonnements premium | E25: =E22*$C$5 | F25: =F22*$C$5 | G25: =G22*$C$5 | H25: =H22*$C$5 | I25: =I22*$C$5 | J25: =J22*$C$5 | K25: =K22*$C$5 | L25: =L22*$C$5 | ... P25: =P22*$C$5 | Q25: =SUM(E25:P25)
D26: Frais sur récompenses débloquées | E26: =E23*$C$6 | F26: =F23*$C$6 | G26: =G23*$C$6 | H26: =H23*$C$6 | I26: =I23*$C$6 | J26: =J23*$C$6 | K26: =K23*$C$6 | L26: =L23*$C$6 | ... P26: =P23*$C$6 | Q26: =SUM(E26:P26)
D27: White-label / pub (saisie) | E27: 0 | F27: 0 | G27: 0 | H27: 0 | I27: 0 | J27: 500 | K27: 1000 | L27: 1000 | M27: 1500 | N27: 1500 | O27: 2000 | P27: 2000 | Q27: =SUM(E27:P27)
D28: CA total | E28: =SUM(E25:E27) | F28: =SUM(F25:F27) | G28: =SUM(G25:G27) | H28: =SUM(H25:H27) | I28: =SUM(I25:I27) | J28: =SUM(J25:J27) | K28: =SUM(K25:K27) | L28: =SUM(L25:L27) | ... P28: =SUM(P25:P27) | Q28: =SUM(E28:P28)
D29: COÛTS (€)
D30: Infra (hébergement, BDD, stockage) | E30: =IF(E$17>=$C$14,$C$13,0) | F30: =IF(F$17>=$C$14,$C$13,0) | G30: =IF(G$17>=$C$14,$C$13,0) | H30: =IF(H$17>=$C$14,$C$13,0) | I30: =IF(I$17>=$C$14,$C$13,0) | J30: =IF(J$17>=$C$14,$C$13,0) | K30: =IF(K$17>=$C$14,$C$13,0) | L30: =IF(L$17>=$C$14,$C$13,0) | ... P30: =IF(P$17>=$C$14,$C$13,0) | Q30: =SUM(E30:P30)
D31: Apple Developer | E31: =IF(E$17>=$C$12,$C$11,0) | F31: =IF(F$17>=$C$12,$C$11,0) | G31: =IF(G$17>=$C$12,$C$11,0) | H31: =IF(H$17>=$C$12,$C$11,0) | I31: =IF(I$17>=$C$12,$C$11,0) | J31: =IF(J$17>=$C$12,$C$11,0) | K31: =IF(K$17>=$C$12,$C$11,0) | L31: =IF(L$17>=$C$12,$C$11,0) | ... P31: =IF(P$17>=$C$12,$C$11,0) | Q31: =SUM(E31:P31)
D32: Nom de domaine | E32: =$C$10 | F32: =$C$10 | G32: =$C$10 | H32: =$C$10 | I32: =$C$10 | J32: =$C$10 | K32: =$C$10 | L32: =$C$10 | ... P32: =$C$10 | Q32: =SUM(E32:P32)
D33: Commissions Stripe | E33: =E25*$C$8+E22*$C$9 | F33: =F25*$C$8+F22*$C$9 | G33: =G25*$C$8+G22*$C$9 | H33: =H25*$C$8+H22*$C$9 | I33: =I25*$C$8+I22*$C$9 | J33: =J25*$C$8+J22*$C$9 | K33: =K25*$C$8+K22*$C$9 | L33: =L25*$C$8+L22*$C$9 | ... P33: =P25*$C$8+P22*$C$9 | Q33: =SUM(E33:P33)
D34: Coûts totaux | E34: =SUM(E30:E33) | F34: =SUM(F30:F33) | G34: =SUM(G30:G33) | H34: =SUM(H30:H33) | I34: =SUM(I30:I33) | J34: =SUM(J30:J33) | K34: =SUM(K30:K33) | L34: =SUM(L30:L33) | ... P34: =SUM(P30:P33) | Q34: =SUM(E34:P34)
D35: RÉSULTAT
D36: Résultat net du mois | E36: =E28-E34 | F36: =F28-F34 | G36: =G28-G34 | H36: =H28-H34 | I36: =I28-I34 | J36: =J28-J34 | K36: =K28-K34 | L36: =L28-L34 | ... P36: =P28-P34 | Q36: =SUM(E36:P36)
D37: Trésorerie cumulée | E37: =E36 | F37: =E37+F36 | G37: =F37+G36 | H37: =G37+H36 | I37: =H37+I36 | J37: =I37+J36 | K37: =J37+K36 | L37: =K37+L36 | M37: =L37+M36 | ... P37: =O37+P36

Sheet Comparaison
B2: Comparaison des 3 scénarios — année 1
B4: Scénario | C4: CA année | D4: Coûts année | E4: Résultat net | F4: CA mensuel M12 | G4: Restos premium M12
B5: Pessimiste (gratter le fond) | C5: ='Modèle'!Q28 | D5: ='Modèle'!Q34 | E5: ='Modèle'!Q36 | F5: ='Modèle'!P28 | G5: ='Modèle'!P22
B6: Réaliste | C6: ='Réaliste'!Q28 | D6: ='Réaliste'!Q34 | E6: ='Réaliste'!Q36 | F6: ='Réaliste'!P28 | G6: ='Réaliste'!P22
B7: Ambitieux | C7: ='Ambitieux'!Q28 | D7: ='Ambitieux'!Q34 | E7: ='Ambitieux'!Q36 | F7: ='Ambitieux'!P28 | G7: ='Ambitieux'!P22
